{"tiles": [{"x1": 0, "y1": 32, "x2": 64, "y2": 64, "tile_id": "618", "grid_size": [32, 32], "assigned_id": 618}, {"x1": 64, "y1": 32, "x2": 128, "y2": 64, "tile_id": "619", "grid_size": [32, 32], "assigned_id": 619}, {"x1": 0, "y1": 96, "x2": 64, "y2": 128, "tile_id": "304", "grid_size": [32, 32], "assigned_id": 304}, {"x1": 64, "y1": 96, "x2": 128, "y2": 128, "tile_id": "303", "grid_size": [32, 32], "assigned_id": 303}, {"x1": 0, "y1": 64, "x2": 64, "y2": 96, "tile_id": "302", "grid_size": [32, 32], "collision_type": "Slope \u25e2", "assigned_id": 302}, {"x1": 64, "y1": 64, "x2": 128, "y2": 96, "tile_id": "301", "grid_size": [32, 32], "collision_type": "Slope \u25e3", "assigned_id": 301}, {"x1": 0, "y1": 0, "x2": 64, "y2": 32, "tile_id": "616", "grid_size": [32, 32], "collision_type": "Slope \u25e2", "assigned_id": 616}, {"x1": 64, "y1": 0, "x2": 128, "y2": 32, "tile_id": "617", "grid_size": [32, 32], "collision_type": "Slope \u25e3", "assigned_id": 617}]}